.gitignore
LICENSE
README.rst
setup.cfg
setup.py
tox.ini
./jenviz/__init__.py
.github/workflows/test.yaml
jenviz/__init__.py
jenviz.egg-info/PKG-INFO
jenviz.egg-info/SOURCES.txt
jenviz.egg-info/dependency_links.txt
jenviz.egg-info/entry_points.txt
jenviz.egg-info/requires.txt
jenviz.egg-info/top_level.txt
snap/snapcraft.yaml